pyobservability/__init__.py
pyobservability/main.py
pyobservability/monitor.py
pyobservability/transport.py
pyobservability/version.py
pyobservability/config/enums.py
pyobservability/config/settings.py
pyobservability/static/app.js
pyobservability/static/styles.css
pyobservability/templates/index.html
pyobservability-1.4.1.dist-info/licenses/LICENSE
pyobservability-1.4.1.dist-info/METADATA
pyobservability-1.4.1.dist-info/WHEEL
pyobservability-1.4.1.dist-info/entry_points.txt
pyobservability-1.4.1.dist-info/top_level.txt
pyobservability-1.4.1.dist-info/RECORD
