Metadata-Version: 2.4
Name: PyObservability
Version: 1.4.1
Summary: Lightweight OS-agnostic observability UI for PyNinja
Author-email: Vignesh Rao <svignesh1793@gmail.com>
License: MIT License
Project-URL: Homepage, https://github.com/thevickypedia/PyObservability
Project-URL: Docs, https://thevickypedia.github.io/PyObservability
Project-URL: Source, https://github.com/thevickypedia/PyObservability
Project-URL: Bug Tracker, https://github.com/thevickypedia/PyObservability/issues
Project-URL: Release Notes, https://github.com/thevickypedia/PyObservability/blob/main/release_notes.md
Keywords: PyObservability,observability,system-monitor,PyNinja
Classifier: License :: OSI Approved :: MIT License
Classifier: Programming Language :: Python :: 3
Classifier: Development Status :: 5 - Production/Stable
Classifier: Operating System :: MacOS :: MacOS X
Classifier: Operating System :: Microsoft :: Windows
Classifier: Operating System :: POSIX :: Linux
Classifier: Topic :: System :: Monitoring
Requires-Python: >=3.11
License-File: LICENSE
Requires-Dist: aiohttp==3.13.*
Requires-Dist: fastapi==0.122.*
Requires-Dist: FastAPI-UI-Auth==0.2.1
Requires-Dist: Jinja2==3.1.*
Requires-Dist: pydantic==2.12.*
Requires-Dist: pydantic-settings==2.12.*
Requires-Dist: python-dotenv==1.2.*
Requires-Dist: uvicorn[standard]==0.38.*
Provides-Extra: dev
Requires-Dist: pre-commit; extra == "dev"
Dynamic: license-file
